<?xml version="1.0" encoding="UTF-8"?>
<odoo>

    <record id="action_veterinarios" model="ir.actions.act_window">
        <field name="name">Veterinarios</field>
        <field name="res_model">gestion_personal_veterinaria.veterinario</field>
        <field name="view_mode">tree,form</field>
    </record>

    <menuitem id="menu_veterinaria_root" name="Veterinaria"/>

    <menuitem id="menu_veterinarios"
            name="Veterinarios"
            parent="menu_veterinaria_root"
            action="action_veterinarios"
            sequence="10"/>
</odoo>
